gouvlu/.DS_Store
gouvlu/__init__.py
gouvlu/views.py
gouvlu/harvesters/__init__.py
gouvlu/harvesters/csv_harvester.py
gouvlu/harvesters/igss-20180627.csv
gouvlu/harvesters/igss.csv
gouvlu/harvesters/igss.py
gouvlu/harvesters/igss.xlsx
gouvlu/harvesters/statec.py
gouvlu/templates/5yearplan.html
gouvlu/templates/api.html
gouvlu/templates/publishing.html
gouvlu/templates/requesting.html
gouvlu/templates/strategy.html
gouvlu/templates/usage.html
gouvlu/templates/faq/base.html
gouvlu/templates/faq/citizen.html
gouvlu/templates/faq/developer.html
gouvlu/templates/faq/home.html
gouvlu/templates/faq/producer.html
gouvlu/templates/faq/reuser.html
gouvlu/templates/faq/system-integrator.html
gouvlu/theme/.DS_Store
gouvlu/theme/__init__.py
gouvlu/theme/babel.cfg
gouvlu/theme/info.json
gouvlu/theme/manifest.json
gouvlu/theme/static/admin.a588d019fe3c4e74d6cb.css
gouvlu/theme/static/admin.a588d019fe3c4e74d6cb.js
gouvlu/theme/static/admin.a588d019fe3c4e74d6cb.js.map
gouvlu/theme/static/oembed.a588d019fe3c4e74d6cb.css
gouvlu/theme/static/oembed.a588d019fe3c4e74d6cb.js
gouvlu/theme/static/oembed.a588d019fe3c4e74d6cb.js.map
gouvlu/theme/static/theme.a588d019fe3c4e74d6cb.css
gouvlu/theme/static/theme.a588d019fe3c4e74d6cb.js
gouvlu/theme/static/theme.a588d019fe3c4e74d6cb.js.map
gouvlu/theme/static/img/certified-stamp.png
gouvlu/theme/static/img/communaute_cover.png
gouvlu/theme/static/img/logo-bloc-borderless.svg
gouvlu/theme/static/img/logo-bloc.svg
gouvlu/theme/static/img/logo-url.svg
gouvlu/theme/static/img/renow.svg
gouvlu/theme/static/img/favicon/114x114.png
gouvlu/theme/static/img/favicon/120x120.png
gouvlu/theme/static/img/favicon/144x144.png
gouvlu/theme/static/img/favicon/152x152.png
gouvlu/theme/static/img/favicon/16x16.png
gouvlu/theme/static/img/favicon/180x180.png
gouvlu/theme/static/img/favicon/192x192.png
gouvlu/theme/static/img/favicon/194x194.png
gouvlu/theme/static/img/favicon/32x32.png
gouvlu/theme/static/img/favicon/57x57.png
gouvlu-2.0.24.dist-info/METADATA
gouvlu-2.0.24.dist-info/WHEEL
gouvlu-2.0.24.dist-info/entry_points.txt
gouvlu-2.0.24.dist-info/top_level.txt
gouvlu-2.0.24.dist-info/RECORD
