Metadata-Version: 2.1
Name: gouvlu
Version: 2.0.24
Summary: Official udata theme and extensions of the Open Data Portal of Luxembourg
Home-page: https://github.com/opendatalu/gouvlu
Author: DataPublicLu
Author-email: info@data.public.lu
License: AGPL
Keywords: udata theme gouvlu
Platform: UNKNOWN
Classifier: Development Status :: 3 - Alpha
Classifier: Programming Language :: Python
Classifier: Environment :: Web Environment
Classifier: Operating System :: OS Independent
Classifier: Intended Audience :: Developers
Classifier: Topic :: System :: Software Distribution
Classifier: Programming Language :: Python
Classifier: Programming Language :: Python :: 3
Classifier: Programming Language :: Python :: 3.7
Classifier: Topic :: Software Development :: Libraries :: Python Modules
Requires-Python: >=3.7
Requires-Dist: udata (==2.7.1)
Requires-Dist: unidecode
Requires-Dist: feedparser
Requires-Dist: beautifulsoup4
Provides-Extra: test
Requires-Dist: mock (==3.0.5) ; extra == 'test'
Requires-Dist: pytest (==4.6.3) ; extra == 'test'
Requires-Dist: pytest-flask (==0.15.0) ; extra == 'test'
Requires-Dist: pytest-mock (==1.10.3) ; extra == 'test'
Requires-Dist: pytest-mock (==2.0.0) ; extra == 'test'
Requires-Dist: requests-mock (==1.7.0) ; extra == 'test'
Requires-Dist: feedgen (==0.7.0) ; extra == 'test'
